README.md
setup.cfg
setup.py
tfa_python_sdk/__init__.py
tfa_python_sdk/tfa_python_sdk.py
tfa_python_sdk.egg-info/PKG-INFO
tfa_python_sdk.egg-info/SOURCES.txt
tfa_python_sdk.egg-info/dependency_links.txt
tfa_python_sdk.egg-info/requires.txt
tfa_python_sdk.egg-info/top_level.txt