Metadata-Version: 2.1
Name: tfa-python-sdk
Version: 1.0.0
Summary: Telegram Factor Authentication python library
Home-page: https://github.com/tele-fa/tfa-python-sdk
Author: Amirhossein Mohammadi
Author-email: amirhosseinmohammadi1380@yahoo.com
License: MIT
Platform: UNKNOWN
